deepagents_cli/__init__.py
deepagents_cli/__main__.py
deepagents_cli/_version.py
deepagents_cli/agent.py
deepagents_cli/app.py
deepagents_cli/app.tcss
deepagents_cli/clipboard.py
deepagents_cli/config.py
deepagents_cli/default_agent_prompt.md
deepagents_cli/file_ops.py
deepagents_cli/image_utils.py
deepagents_cli/input.py
deepagents_cli/local_context.py
deepagents_cli/main.py
deepagents_cli/project_utils.py
deepagents_cli/py.typed
deepagents_cli/sessions.py
deepagents_cli/shell.py
deepagents_cli/subagents.py
deepagents_cli/textual_adapter.py
deepagents_cli/tools.py
deepagents_cli/ui.py
deepagents_cli/integrations/__init__.py
deepagents_cli/integrations/daytona.py
deepagents_cli/integrations/modal.py
deepagents_cli/integrations/runloop.py
deepagents_cli/integrations/sandbox_factory.py
deepagents_cli/skills/__init__.py
deepagents_cli/skills/commands.py
deepagents_cli/skills/load.py
deepagents_cli/widgets/__init__.py
deepagents_cli/widgets/approval.py
deepagents_cli/widgets/autocomplete.py
deepagents_cli/widgets/chat_input.py
deepagents_cli/widgets/diff.py
deepagents_cli/widgets/history.py
deepagents_cli/widgets/loading.py
deepagents_cli/widgets/messages.py
deepagents_cli/widgets/status.py
deepagents_cli/widgets/tool_renderers.py
deepagents_cli/widgets/tool_widgets.py
deepagents_cli/widgets/welcome.py
deepagents_cli-0.0.15.dist-info/METADATA
deepagents_cli-0.0.15.dist-info/WHEEL
deepagents_cli-0.0.15.dist-info/entry_points.txt
deepagents_cli-0.0.15.dist-info/top_level.txt
deepagents_cli-0.0.15.dist-info/RECORD
