Metadata-Version: 2.4
Name: deepagents-cli
Version: 0.0.15
Summary: Deepagents CLI
License: MIT
Requires-Python: <4.0,>=3.11
Requires-Dist: deepagents==0.3.9
Requires-Dist: langchain<2.0.0,>=1.2.7
Requires-Dist: langchain-openai<2.0.0,>=1.1.7
Requires-Dist: langgraph-checkpoint-sqlite<4.0.0,>=3.0.0
Requires-Dist: requests
Requires-Dist: rich>=13.0.0
Requires-Dist: prompt-toolkit>=3.0.52
Requires-Dist: tavily-python
Requires-Dist: python-dotenv
Requires-Dist: daytona>=0.113.0
Requires-Dist: modal>=0.65.0
Requires-Dist: markdownify>=0.13.0
Requires-Dist: runloop-api-client>=0.69.0
Requires-Dist: pillow>=10.0.0
Requires-Dist: pyyaml>=6.0
Requires-Dist: textual>=1.0.0
Requires-Dist: textual-autocomplete>=3.0.0
Requires-Dist: aiosqlite>=0.19.0
Provides-Extra: vertexai
Requires-Dist: langchain-google-vertexai<4.0.0,>=3.0.0; extra == "vertexai"
